ProtWave_VAE/__init__.py
ProtWave_VAE/model_components.py
ProtWave_VAE/model_ensemble.py
ProtWave_VAE/wavenet_decoder.py
src/__init__.py
src/model_components.py
src/model_ensemble.py
src/wavenet_decoder.py
ProtWave_VAE-0.0.4.dist-info/LICENSE
ProtWave_VAE-0.0.4.dist-info/METADATA
ProtWave_VAE-0.0.4.dist-info/WHEEL
ProtWave_VAE-0.0.4.dist-info/top_level.txt
ProtWave_VAE-0.0.4.dist-info/RECORD
